{"v":5,"entries":{"introduction--docs":{"id":"introduction--docs","title":"Introduction","name":"Docs","importPath":"./src/storybook/Introduction.mdx","storiesImports":[],"type":"docs","tags":["dev","test","unattached-mdx"]},"theme-colours--docs":{"id":"theme-colours--docs","title":"Theme/Colours","name":"Docs","importPath":"./src/storybook/theme/Colours.mdx","storiesImports":[],"type":"docs","tags":["dev","test","unattached-mdx"]},"scireactui-basic-basicbutton--docs":{"id":"scireactui-basic-basicbutton--docs","title":"SciReactUI/Basic/BasicButton","name":"Docs","importPath":"./src/components/BasicButton.stories.tsx","type":"docs","tags":["dev","test","autodocs"],"storiesImports":[]},"scireactui-basic-basicbutton--primary":{"type":"story","id":"scireactui-basic-basicbutton--primary","name":"Primary","title":"SciReactUI/Basic/BasicButton","importPath":"./src/components/BasicButton.stories.tsx","componentPath":"./src/components/BasicButton.tsx","tags":["dev","test","autodocs"]},"scireactui-basic-basicbutton--variants":{"type":"story","id":"scireactui-basic-basicbutton--variants","name":"Variants","title":"SciReactUI/Basic/BasicButton","importPath":"./src/components/BasicButton.stories.tsx","componentPath":"./src/components/BasicButton.tsx","tags":["dev","test","autodocs"]},"scireactui-basic-basicbutton--disabled":{"type":"story","id":"scireactui-basic-basicbutton--disabled","name":"Disabled","title":"SciReactUI/Basic/BasicButton","importPath":"./src/components/BasicButton.stories.tsx","componentPath":"./src/components/BasicButton.tsx","tags":["dev","test","autodocs"]},"scireactui-basic-basicbutton--secondary-colour":{"type":"story","id":"scireactui-basic-basicbutton--secondary-colour","name":"Secondary Colour","title":"SciReactUI/Basic/BasicButton","importPath":"./src/components/BasicButton.stories.tsx","componentPath":"./src/components/BasicButton.tsx","tags":["dev","test","autodocs"]},"scireactui-navigation-navbar--docs":{"id":"scireactui-navigation-navbar--docs","title":"SciReactUI/Navigation/Navbar","name":"Docs","importPath":"./src/components/Navbar.stories.tsx","type":"docs","tags":["dev","test","autodocs"],"storiesImports":[]},"scireactui-navigation-navbar--empty":{"type":"story","id":"scireactui-navigation-navbar--empty","name":"Empty","title":"SciReactUI/Navigation/Navbar","importPath":"./src/components/Navbar.stories.tsx","componentPath":"./src/components/Navbar.tsx","tags":["dev","test","autodocs"]},"scireactui-navigation-navbar--with-login":{"type":"story","id":"scireactui-navigation-navbar--with-login","name":"With Login","title":"SciReactUI/Navigation/Navbar","importPath":"./src/components/Navbar.stories.tsx","componentPath":"./src/components/Navbar.tsx","tags":["dev","test","autodocs"]},"scireactui-navigation-navbar--with-user":{"type":"story","id":"scireactui-navigation-navbar--with-user","name":"With User","title":"SciReactUI/Navigation/Navbar","importPath":"./src/components/Navbar.stories.tsx","componentPath":"./src/components/Navbar.tsx","tags":["dev","test","autodocs"]},"scireactui-navigation-navbar--links":{"type":"story","id":"scireactui-navigation-navbar--links","name":"Links","title":"SciReactUI/Navigation/Navbar","importPath":"./src/components/Navbar.stories.tsx","componentPath":"./src/components/Navbar.tsx","tags":["dev","test","autodocs"]},"scireactui-navigation-navbar--links-and-user":{"type":"story","id":"scireactui-navigation-navbar--links-and-user","name":"Links And User","title":"SciReactUI/Navigation/Navbar","importPath":"./src/components/Navbar.stories.tsx","componentPath":"./src/components/Navbar.tsx","tags":["dev","test","autodocs"]},"scireactui-navigation-navbar--no-logo":{"type":"story","id":"scireactui-navigation-navbar--no-logo","name":"No Logo","title":"SciReactUI/Navigation/Navbar","importPath":"./src/components/Navbar.stories.tsx","componentPath":"./src/components/Navbar.tsx","tags":["dev","test","autodocs"]},"scireactui-navigation-navbar--custom-child-element":{"type":"story","id":"scireactui-navigation-navbar--custom-child-element","name":"Custom Child Element","title":"SciReactUI/Navigation/Navbar","importPath":"./src/components/Navbar.stories.tsx","componentPath":"./src/components/Navbar.tsx","tags":["dev","test","autodocs"]},"scireactui-control-user--docs":{"id":"scireactui-control-user--docs","title":"SciReactUI/Control/User","name":"Docs","importPath":"./src/components/User.stories.tsx","type":"docs","tags":["dev","test","autodocs"],"storiesImports":[]},"scireactui-control-user--logged-out":{"type":"story","id":"scireactui-control-user--logged-out","name":"Logged Out","title":"SciReactUI/Control/User","importPath":"./src/components/User.stories.tsx","componentPath":"./src/components/User.tsx","tags":["dev","test","autodocs"]},"scireactui-control-user--logged-in":{"type":"story","id":"scireactui-control-user--logged-in","name":"Logged In","title":"SciReactUI/Control/User","importPath":"./src/components/User.stories.tsx","componentPath":"./src/components/User.tsx","tags":["dev","test","autodocs"]},"scireactui-control-user--logged-in-no-name":{"type":"story","id":"scireactui-control-user--logged-in-no-name","name":"Logged In No Name","title":"SciReactUI/Control/User","importPath":"./src/components/User.stories.tsx","componentPath":"./src/components/User.tsx","tags":["dev","test","autodocs"]},"scireactui-control-user--logged-in-long-name":{"type":"story","id":"scireactui-control-user--logged-in-long-name","name":"Logged In Long Name","title":"SciReactUI/Control/User","importPath":"./src/components/User.stories.tsx","componentPath":"./src/components/User.tsx","tags":["dev","test","autodocs"]},"scireactui-control-user--logged-in-change-color":{"type":"story","id":"scireactui-control-user--logged-in-change-color","name":"Logged In Change Color","title":"SciReactUI/Control/User","importPath":"./src/components/User.stories.tsx","componentPath":"./src/components/User.tsx","tags":["dev","test","autodocs"]},"scireactui-control-user--logged-in-replace-avatar":{"type":"story","id":"scireactui-control-user--logged-in-replace-avatar","name":"Logged In Replace Avatar","title":"SciReactUI/Control/User","importPath":"./src/components/User.stories.tsx","componentPath":"./src/components/User.tsx","tags":["dev","test","autodocs"]},"scireactui-control-visitinput--docs":{"id":"scireactui-control-visitinput--docs","title":"SciReactUI/Control/VisitInput","name":"Docs","importPath":"./src/components/VisitInput.stories.tsx","type":"docs","tags":["dev","test","autodocs"],"storiesImports":[]},"scireactui-control-visitinput--input":{"type":"story","id":"scireactui-control-visitinput--input","name":"Input","title":"SciReactUI/Control/VisitInput","importPath":"./src/components/VisitInput.stories.tsx","componentPath":"./src/components/VisitInput.tsx","tags":["dev","test","autodocs"]},"scireactui-control-visitinput--initial-visit":{"type":"story","id":"scireactui-control-visitinput--initial-visit","name":"Initial Visit","title":"SciReactUI/Control/VisitInput","importPath":"./src/components/VisitInput.stories.tsx","componentPath":"./src/components/VisitInput.tsx","tags":["dev","test","autodocs"]},"scireactui-control-visitinput--input-with-submit":{"type":"story","id":"scireactui-control-visitinput--input-with-submit","name":"Input With Submit","title":"SciReactUI/Control/VisitInput","importPath":"./src/components/VisitInput.stories.tsx","componentPath":"./src/components/VisitInput.tsx","tags":["dev","test","autodocs"]},"scireactui-control-visitinput--initial-visit-with-submit":{"type":"story","id":"scireactui-control-visitinput--initial-visit-with-submit","name":"Initial Visit With Submit","title":"SciReactUI/Control/VisitInput","importPath":"./src/components/VisitInput.stories.tsx","componentPath":"./src/components/VisitInput.tsx","tags":["dev","test","autodocs"]}}}